replies/__init__.py
replies-0.0.1.dist-info/WHEEL
replies-0.0.1.dist-info/METADATA
replies-0.0.1.dist-info/RECORD
